powerbiclient/__init__.py
powerbiclient/_version.py
powerbiclient/authentication.py
powerbiclient/models.py
powerbiclient/quick_visualize.py
powerbiclient/report.py
powerbiclient/utils.py
powerbiclient/labextension/powerbi-jupyter-client-3.1.0.tgz
powerbiclient/nbextension/__init__.py
powerbiclient/nbextension/static/extension.js
powerbiclient/nbextension/static/index.js
powerbiclient/nbextension/static/index.js.LICENSE.txt
powerbiclient/nbextension/static/index.js.map
powerbiclient/tests/__init__.py
powerbiclient/tests/conftest.py
powerbiclient/tests/test_nbextension_path.py
powerbiclient/tests/test_quick_visualize.py
powerbiclient/tests/test_report.py
powerbiclient/tests/test_utils.py
powerbiclient/tests/utils.py
powerbiclient-3.1.0.data/data/etc/jupyter/nbconfig/notebook.d/powerbiclient.json
powerbiclient-3.1.0.data/data/share/jupyter/lab/extensions/powerbi-jupyter-client-3.1.0.tgz
powerbiclient-3.1.0.data/data/share/jupyter/nbextensions/powerbiclient/extension.js
powerbiclient-3.1.0.data/data/share/jupyter/nbextensions/powerbiclient/index.js
powerbiclient-3.1.0.data/data/share/jupyter/nbextensions/powerbiclient/index.js.LICENSE.txt
powerbiclient-3.1.0.data/data/share/jupyter/nbextensions/powerbiclient/index.js.map
powerbiclient-3.1.0.dist-info/LICENSE.txt
powerbiclient-3.1.0.dist-info/METADATA
powerbiclient-3.1.0.dist-info/WHEEL
powerbiclient-3.1.0.dist-info/top_level.txt
powerbiclient-3.1.0.dist-info/RECORD
