Metadata-Version: 2.1
Name: powerbiclient
Version: 3.1.0
Summary: A Custom Jupyter Widget Library
Home-page: https://github.com/Microsoft/powerbi-jupyter
Author: Microsoft
Author-email: 
License: MIT
Keywords: Jupyter,Widgets,IPython
Platform: Linux
Platform: Mac OS X
Platform: Windows
Classifier: Intended Audience :: Developers
Classifier: License :: OSI Approved :: MIT License
Classifier: Programming Language :: Python
Classifier: Programming Language :: Python :: 3.7
Classifier: Programming Language :: Python :: 3.8
Classifier: Programming Language :: Python :: 3.9
Classifier: Framework :: Jupyter
Requires-Python: >=3.4
License-File: LICENSE.txt
Requires-Dist: ipywidgets (>=7.0.0)
Requires-Dist: jupyter-ui-poll (>=0.1.2)
Requires-Dist: msal (>=1.8.0)
Requires-Dist: requests (>=2.25.1)
Requires-Dist: pandas
Requires-Dist: pyspark
Provides-Extra: demo
Requires-Dist: pandas ; extra == 'demo'
Requires-Dist: matplotlib ; extra == 'demo'
Provides-Extra: test
Requires-Dist: pytest (>=4.6) ; extra == 'test'
Requires-Dist: pytest-cov ; extra == 'test'
Requires-Dist: nbval ; extra == 'test'
Requires-Dist: requests-mock ; extra == 'test'
Requires-Dist: mock ; extra == 'test'
